{
  "project_info": {
    "project_number": "118167251168",
    "project_id": "walletwise-hcmus2024",
    "storage_bucket": "walletwise-hcmus2024.appspot.com"
  },
  "client": [
    {
      "client_info": {
        "mobilesdk_app_id": "1:118167251168:android:6426164e60b1074a5cc885",
        "android_client_info": {
          "package_name": "com.finance.android.walletwise"
        }
      },
      "oauth_client": [],
      "api_key": [
        {
          "current_key": "AIzaSyDpWKFwBlaOzxsQyFJ65PIORGefmDeucvk"
        }
      ],
      "services": {
        "appinvite_service": {
          "other_platform_oauth_client": []
        }
      }
    }
  ],
  "configuration_version": "1"
}